trembala/__init__.py
trembala-0.0.0.dist-info/LICENSE
trembala-0.0.0.dist-info/METADATA
trembala-0.0.0.dist-info/WHEEL
trembala-0.0.0.dist-info/top_level.txt
trembala-0.0.0.dist-info/RECORD
