Metadata-Version: 2.1
Name: trembala
Version: 0.0.0
Summary: Trembala: Um framework inovador e rápido.
Home-page: https://github.com/ArturArantes/trembala
Author: Artur Arantes Santos da Silva
Author-email: contact@trembao.dev
Classifier: Programming Language :: Python :: 3
Classifier: License :: OSI Approved :: MIT License
Classifier: Operating System :: OS Independent
Requires-Python: >=3.6
License-File: LICENSE
